docs/conf.py
enkie/README.md
enkie/__init__.py
enkie/commons.py
enkie/compartment_parameters.py
enkie/constants.py
enkie/distributions.py
enkie/enzyme.py
enkie/metabolite.py
enkie/miriam_metabolite.py
enkie/miriam_reaction.py
enkie/modular_rate_law.py
enkie/parameter_space.py
enkie/reaction.py
enkie/singleton_meta.py
enkie/storage.py
enkie/utils.py
enkie/console/cli.py
enkie/data/__init__.py
enkie/data/ecs_curation.csv
enkie/data/kinetics_prior_brenda.csv
enkie/data/kinetics_prior_wide.csv
enkie/data/metabolite_mappings_curation.csv
enkie/data/reaction_mappings_curation.csv
enkie/data/compartment_parameters/__init__.py
enkie/data/compartment_parameters/default.csv
enkie/data/compartment_parameters/e_coli.csv
enkie/data/compartment_parameters/human.csv
enkie/dbs/__init__.py
enkie/dbs/kegg.py
enkie/dbs/metanetx.py
enkie/dbs/uniprot.py
enkie/estimators/__init__.py
enkie/estimators/bmm_kinetic_estimator.py
enkie/estimators/equilibrator_gibbs_estimator.py
enkie/estimators/fixed_kinetics_estimator.py
enkie/estimators/gibbs_estimator_interface.py
enkie/estimators/kinetic_parameter_types.py
enkie/estimators/kinetics_estimator_interface.py
enkie/estimators/parameter_balancer.py
enkie/io/__init__.py
enkie/io/cobra.py
tests/conftest.py
tests/test_bmm_estimator.py
tests/test_equilibrator_gibbs_estimator.py
tests/test_parameter_balancing.py
tests/test_parameter_space.py
training/data/a_merge_databases.py
training/data/b_add_proteins.py
training/data/c_add_families.py
training/data/d_split_ecs.py
training/data/e_cleanup.py
training/data/f_summary.py
training/data/g_create_splits.py
training/data/h_create_random_splits.py
training/data/brenda/a_brenda_parse.py
training/data/brenda/b_brenda_metanetx_ids.py
training/data/sabio-rk/a_main.py
training/data/sabio-rk/b_add_ncbi_ids.py
training/data/sabio-rk/c_split_ec_number.py
training/data/sabio-rk/d_add_substrate_mnx_ids.py
venv/bin/activate_this.py
enkie-0.1.3.dist-info/LICENSE
enkie-0.1.3.dist-info/METADATA
enkie-0.1.3.dist-info/WHEEL
enkie-0.1.3.dist-info/entry_points.txt
enkie-0.1.3.dist-info/top_level.txt
enkie-0.1.3.dist-info/zip-safe
enkie-0.1.3.dist-info/RECORD
