Metadata-Version: 2.1
Name: enkie
Version: 0.1.3
Summary: ENKIE - The ENzyme KInetics Estimator
Author-email: Mattia Gollub <mattia.gollub@gmail.com>
License: MIT License
Project-URL: repository, https://gitlab.com/csb.ethz/enkie
Project-URL: documentation, https://enkie.readthedocs.io/en/latest/
Keywords: enzyme,kinetics,catalytic rate,affinity,thermodynamics,estimation,metabolism,metabolic networks
Classifier: Development Status :: 4 - Beta
Classifier: Intended Audience :: Science/Research
Classifier: Topic :: Scientific/Engineering :: Bio-Informatics
Classifier: License :: OSI Approved :: MIT License
Classifier: Natural Language :: English
Classifier: Programming Language :: Python :: 3
Classifier: Programming Language :: Python :: 3.8
Classifier: Programming Language :: Python :: 3.9
Classifier: Programming Language :: Python :: 3.10
Classifier: Programming Language :: Python :: 3.11
Requires-Python: >=3.8
License-File: LICENSE
Requires-Dist: click~=8.1.3
Requires-Dist: cobra~=0.29.1
Requires-Dist: equilibrator-api~=0.4.7
Requires-Dist: platformdirs~=3.0.0
Requires-Dist: requests-cache~=0.9.4
Requires-Dist: rpy2~=3.5.7
Requires-Dist: pooch~=1.8.2
Provides-Extra: test
Requires-Dist: pytest; extra == "test"
Requires-Dist: pytest-lazy-fixture; extra == "test"
